mahendra_periodic_table-0.1.dist-info/DESCRIPTION.rst
mahendra_periodic_table-0.1.dist-info/METADATA
mahendra_periodic_table-0.1.dist-info/RECORD
mahendra_periodic_table-0.1.dist-info/WHEEL
mahendra_periodic_table-0.1.dist-info/metadata.json
mahendra_periodic_table-0.1.dist-info/top_level.txt
periodic_table/__init__.py
periodic_table/ptable.py
