Metadata-Version: 2.0
Name: mahendra-periodic-table
Version: 0.1
Summary: chemistry symbols and name
Home-page: UNKNOWN
Author: mahendra
Author-email: mahendra.k12@gmail.com
License: MIT
Platform: UNKNOWN
